freqtrade_custom_indicators/__init__.py
freqtrade_custom_indicators/squeeze.py
freqtrade_custom_indicators/tsv.py
freqtrade_custom_indicators-0.2.3.dist-info/LICENSE
freqtrade_custom_indicators-0.2.3.dist-info/WHEEL
freqtrade_custom_indicators-0.2.3.dist-info/METADATA
freqtrade_custom_indicators-0.2.3.dist-info/RECORD
