Metadata-Version: 2.1
Name: freqtrade-custom-indicators
Version: 0.2.3
Summary: Custom indicators for the freqtrade bot
Home-page: https://github.com/ryanleecode/freqtrade_custom_indicators
License: MIT
Author: freqtrade_custom_indicators
Author-email: ryanleecode@gmail.com
Requires-Python: >=3.9,<4.0
Classifier: Development Status :: 3 - Alpha
Classifier: Intended Audience :: Developers
Classifier: License :: OSI Approved :: MIT License
Classifier: Operating System :: OS Independent
Classifier: Programming Language :: Python :: 3
Classifier: Programming Language :: Python :: 3.10
Classifier: Programming Language :: Python :: 3.9
Classifier: Topic :: Software Development :: Libraries :: Python Modules
Requires-Dist: TA-Lib (>=0.4.24,<0.5.0)
Requires-Dist: numpy (>=1.22.3,<2.0.0)
Requires-Dist: pandas (>=1.4.2,<2.0.0)
Project-URL: Repository, https://github.com/ryanleecode/freqtrade_custom_indicators
